[{"name":"sql.active_record","payload":{"sql":"BEGIN","name":null,"connection_id":2211880340,"binds":[]},"time":"2014-02-04T17:20:41-08:00","transaction_id":"ebea7525db1d8104ff5a","end":"2014-02-04T17:20:41-08:00","children":[],"duration":0.279},{"name":"sql.active_record","payload":{"sql":"SHOW search_path","name":"SCHEMA","connection_id":2211880340,"binds":[]},"time":"2014-02-04T17:20:41-08:00","transaction_id":"ebea7525db1d8104ff5a","end":"2014-02-04T17:20:41-08:00","children":[],"duration":0.275},{"name":"sql.active_record","payload":{"sql":"INSERT INTO \"videos\" (\"created_at\", \"updated_at\") VALUES ($1, $2) RETURNING \"id\"","name":"SQL","connection_id":2211880340,"binds":[[{"oid_type":{},"array":false,"name":"created_at","sql_type":"timestamp without time zone","null":true,"limit":null,"precision":null,"scale":null,"type":"datetime","default":null,"default_function":null,"primary":false,"coder":null},"2014-02-05T01:20:41.600Z"],[{"oid_type":{},"array":false,"name":"updated_at","sql_type":"timestamp without time zone","null":true,"limit":null,"precision":null,"scale":null,"type":"datetime","default":null,"default_function":null,"primary":false,"coder":null},"2014-02-05T01:20:41.600Z"]]},"time":"2014-02-04T17:20:41-08:00","transaction_id":"ebea7525db1d8104ff5a","end":"2014-02-04T17:20:41-08:00","children":[],"duration":3.9360000000000004},{"name":"sql.active_record","payload":{"sql":"COMMIT","name":null,"connection_id":2211880340,"binds":[]},"time":"2014-02-04T17:20:41-08:00","transaction_id":"ebea7525db1d8104ff5a","end":"2014-02-04T17:20:41-08:00","children":[],"duration":7.271},{"name":"sql.active_record","payload":{"sql":"SELECT  \"users\".* FROM \"users\"  WHERE \"users\".\"remember_token\" = 'JmogupCJYYp2K3pubANTPw' LIMIT 1","name":"User Load","connection_id":2211880340,"binds":[]},"time":"2014-02-04T17:20:41-08:00","transaction_id":"ebea7525db1d8104ff5a","end":"2014-02-04T17:20:41-08:00","children":[],"duration":0.664},{"name":"sql.active_record","payload":{"sql":"BEGIN","name":null,"connection_id":2211880340,"binds":[]},"time":"2014-02-04T17:20:41-08:00","transaction_id":"ebea7525db1d8104ff5a","end":"2014-02-04T17:20:41-08:00","children":[],"duration":0.46},{"name":"sql.active_record","payload":{"sql":"UPDATE \"videos\" SET \"url\" = $1, \"extension\" = $2, \"session_id\" = $3, \"delete_key\" = $4, \"updated_at\" = $5 WHERE \"videos\".\"id\" = 2","name":"SQL","connection_id":2211880340,"binds":[[{"oid_type":{},"array":false,"name":"url","sql_type":"character varying(255)","null":true,"limit":255,"precision":null,"scale":null,"type":"string","default":null,"default_function":null,"primary":null,"coder":null},"http://d1f5gutkqysysk.cloudfront.net/uploads%2F1391563236071-tq0akqp39nj6ecdi-ef47db7a9afa9f050bb2992886f8f4c0%2FUntitled.mp4"],[{"oid_type":{},"array":false,"name":"extension","sql_type":"character varying(255)","null":true,"limit":255,"precision":null,"scale":null,"type":"string","default":null,"default_function":null,"primary":null,"coder":null},"mp4"],[{"oid_type":{},"array":false,"name":"session_id","sql_type":"character varying(255)","null":true,"limit":255,"precision":null,"scale":null,"type":"string","default":null,"default_function":null,"primary":null,"coder":null},"9h0bNBQKyycOTQH4PnME"],[{"oid_type":{},"array":false,"name":"delete_key","sql_type":"character varying(255)","null":true,"limit":255,"precision":null,"scale":null,"type":"string","default":null,"default_function":null,"primary":null,"coder":null},"eCtB_89_eguykGVAvTnA-McupMuBzxNGh7rYmY2l"],[{"oid_type":{},"array":false,"name":"updated_at","sql_type":"timestamp without time zone","null":true,"limit":null,"precision":null,"scale":null,"type":"datetime","default":null,"default_function":null,"primary":null,"coder":null},"2014-02-05T01:20:41.615Z"]]},"time":"2014-02-04T17:20:41-08:00","transaction_id":"ebea7525db1d8104ff5a","end":"2014-02-04T17:20:41-08:00","children":[],"duration":1.4009999999999998},{"name":"sql.active_record","payload":{"sql":"COMMIT","name":null,"connection_id":2211880340,"binds":[]},"time":"2014-02-04T17:20:41-08:00","transaction_id":"ebea7525db1d8104ff5a","end":"2014-02-04T17:20:41-08:00","children":[],"duration":0.6759999999999999},{"name":"process_action.action_controller","payload":{"controller":"VideosController","action":"create","params":{"url":"https://videosok.s3.amazonaws.com/uploads%2F1391563236071-tq0akqp39nj6ecdi-ef47db7a9afa9f050bb2992886f8f4c0%2FUntitled.mp4","filepath":"/uploads%2F1391563236071-tq0akqp39nj6ecdi-ef47db7a9afa9f050bb2992886f8f4c0%2FUntitled.mp4","filename":"Untitled.mp4","filesize":"3646244","filetype":"video/mp4","unique_id":"tq0akqp39nj6ecdi","document":{"file_url":"https://videosok.s3.amazonaws.com/uploads%2F1391563236071-tq0akqp39nj6ecdi-ef47db7a9afa9f050bb2992886f8f4c0%2FUntitled.mp4"},"action":"create","controller":"videos"},"format":"*/*","method":"POST","path":"/videos","status":200,"view_runtime":0.132,"db_runtime":13.032000000000002},"time":"2014-02-04T17:20:41-08:00","transaction_id":"26d8ba63972b59caf551","end":"2014-02-04T17:20:41-08:00","children":[],"duration":27.158}]